pretrained/__init__.py
pretrained/blip.py
pretrained/causal_hubert.py
pretrained/clip.py
pretrained/demucs.py
pretrained/encodec.py
pretrained/hubert.py
pretrained/llama.py
pretrained/mel_codec.py
pretrained/py.typed
pretrained/rwkv.py
pretrained/sam.py
pretrained/tacotron2.py
pretrained/wav_codec.py
pretrained/triton/__init__.py
pretrained/triton/rwkv_kernel.py
pretrained/vocoder/__init__.py
pretrained/vocoder/hifigan.py
pretrained/vocoder/waveglow.py
ml_pretrained-0.0.46.dist-info/LICENSE
ml_pretrained-0.0.46.dist-info/METADATA
ml_pretrained-0.0.46.dist-info/WHEEL
ml_pretrained-0.0.46.dist-info/top_level.txt
ml_pretrained-0.0.46.dist-info/RECORD
