Metadata-Version: 2.1
Name: ml-pretrained
Version: 0.0.46
Summary: ML project template repository
Home-page: https://github.com/codekansas/ml-pretrained
Author: Benjamin Bolte
Classifier: Development Status :: 4 - Beta
Classifier: Intended Audience :: Developers
Classifier: Topic :: Scientific/Engineering :: Artificial Intelligence
Classifier: License :: OSI Approved :: MIT License
Classifier: Programming Language :: Python :: 3
Requires-Python: >=3.10
License-File: LICENSE
Requires-Dist: ml-starter
Requires-Dist: safetensors
Provides-Extra: dev
Requires-Dist: ml-starter[dev] ; extra == 'dev'
Provides-Extra: docs
Requires-Dist: ml-starter[docs] ; extra == 'docs'
